flatgfa-0.2.0.dist-info/METADATA
flatgfa-0.2.0.dist-info/WHEEL
flatgfa/__init__.py
flatgfa/__init__.pyi
flatgfa/py.typed
flatgfa/flatgfa.abi3.so
flatgfa-0.2.0.dist-info/RECORD
