Metadata-Version: 2.3
Name: flatgfa
Version: 0.2.0
Classifier: Topic :: Scientific/Engineering :: Bio-Informatics
Classifier: License :: OSI Approved :: MIT License
Requires-Dist: pytest ; extra == 'test'
Provides-Extra: test
Summary: efficient processing of pangenomes in Graphical Fragment Assembly (GFA) format
Keywords: genomics,pangenomics,gfa
License: MIT
Requires-Python: >=3.8
Project-URL: repository, https://github.com/cucapra/pollen
Project-URL: documentation, https://cucapra.github.io/pollen/flatgfa/
